mtclabpy/__init__.py
mtclabpy/Enzyme_Self_Calc/Enzyme_Self_Calc.py
mtclabpy/Enzyme_Self_Calc/__init__.py
mtclabpy/affinities/Affinity_calculation_toolbox1.py
mtclabpy/affinities/__init__.py
mtclabpy/developmental_tree/Developmental_Tree_Digitizing_Numbering_and_Distance_Calculation_Conversion.py
mtclabpy/developmental_tree/Distance_matrix_to_developmental_tree_file.py
mtclabpy/developmental_tree/Facilitating_the_construction_of_developmental_trees_by_Mafft.py
mtclabpy/developmental_tree/__init__.py
mtclabpy/developmental_tree/foldseek_Multiple_Sequence_Comparison.py
mtclabpy/developmental_tree/foldseek_alntmscore.py
mtclabpy/developmental_tree/foldseek_cluster_analysis.py
mtclabpy/developmental_tree/structure_comparison_3d.py
mtclabpy/kcat_prediction/Tustkcat1.py
mtclabpy/kcat_prediction/Tustkcat2.py
mtclabpy/kcat_prediction/__init__.py
mtclabpy/kcat_prediction/dlkcat.py
mtclabpy/kcat_prediction/get_reaction_smiles.py
mtclabpy/kcat_prediction/kcat3.py
mtclabpy/molecular_docking/__init__.py
mtclabpy/molecular_docking/autodock_ff.py
mtclabpy/molecular_docking/autodock_ff_one_protein_multi_ligands.py
mtclabpy/molecular_docking/autodock_vina.py
mtclabpy/molecular_docking/docking_box_analysis.py
mtclabpy/molecular_docking/multi_ligands_docking_by_vina.py
mtclabpy/molecular_docking/protein_ligand_Interaction_Analysis.py
mtclabpy/molecular_pockets/Caverdocking_Toolbox_1.py
mtclabpy/molecular_pockets/__init__.py
mtclabpy/molecular_pockets/activesite_pH_calculation.py
mtclabpy/molecular_pockets/fpocket.py
mtclabpy/molecular_pockets/pockets_calculation_by_CAVER.py
mtclabpy/mutations/CTR_projections.py
mtclabpy/mutations/__init__.py
mtclabpy/mutations/ddG_Prediction_Toolbox.py
mtclabpy/mutations/geoStab_prediction.py
mtclabpy/mutations/pssm_locus_information_organizer.py
mtclabpy/mutations/pssm_online_generation_tool .py
mtclabpy/mutations/pssm_online_generation_tool.py
mtclabpy/mutations/seq_mutation_generation.py
mtclabpy-0.6.8.dist-info/METADATA
mtclabpy-0.6.8.dist-info/WHEEL
mtclabpy-0.6.8.dist-info/top_level.txt
mtclabpy-0.6.8.dist-info/RECORD
