Metadata-Version: 2.1
Name: mtclabpy
Version: 0.6.8
Summary: A comprehensive tool for molecular and enzyme calculations
Home-page: 
Author: Menglei Xia
Author-email: xiamenglei321@163.com
Classifier: Programming Language :: Python :: 3
Classifier: License :: OSI Approved :: MIT License
Classifier: Operating System :: OS Independent
Requires-Python: >=3.6
Requires-Dist: numpy
Requires-Dist: pandas
Requires-Dist: scipy
Requires-Dist: biopython
Requires-Dist: requests
